eclcli/__init__.py
eclcli/i18n.py
eclcli/shell.py
eclcli/api/__init__.py
eclcli/api/api.py
eclcli/api/auth.py
eclcli/api/auth_plugin.py
eclcli/api/eclsdk.py
eclcli/api/image_v1.py
eclcli/api/image_v2.py
eclcli/api/utils.py
eclcli/bare/__init__.py
eclcli/bare/bare_utils.py
eclcli/bare/client.py
eclcli/bare/bareclient/__init__.py
eclcli/bare/bareclient/auth_plugin.py
eclcli/bare/bareclient/base.py
eclcli/bare/bareclient/client.py
eclcli/bare/bareclient/crypto.py
eclcli/bare/bareclient/exceptions.py
eclcli/bare/bareclient/extension.py
eclcli/bare/bareclient/i18n.py
eclcli/bare/bareclient/service_catalog.py
eclcli/bare/bareclient/utils.py
eclcli/bare/bareclient/ecl/__init__.py
eclcli/bare/bareclient/ecl/common/__init__.py
eclcli/bare/bareclient/ecl/common/_i18n.py
eclcli/bare/bareclient/ecl/common/cliutils.py
eclcli/bare/bareclient/ecl/common/uuidutils.py
eclcli/bare/bareclient/ecl/common/apiclient/__init__.py
eclcli/bare/bareclient/ecl/common/apiclient/auth.py
eclcli/bare/bareclient/ecl/common/apiclient/base.py
eclcli/bare/bareclient/ecl/common/apiclient/client.py
eclcli/bare/bareclient/ecl/common/apiclient/exceptions.py
eclcli/bare/bareclient/ecl/common/apiclient/fake_client.py
eclcli/bare/bareclient/ecl/common/apiclient/utils.py
eclcli/bare/bareclient/v2/__init__.py
eclcli/bare/bareclient/v2/availability_zones.py
eclcli/bare/bareclient/v2/client.py
eclcli/bare/bareclient/v2/flavors.py
eclcli/bare/bareclient/v2/images.py
eclcli/bare/bareclient/v2/keypairs.py
eclcli/bare/bareclient/v2/limits.py
eclcli/bare/bareclient/v2/metadata.py
eclcli/bare/bareclient/v2/ports.py
eclcli/bare/bareclient/v2/servers.py
eclcli/bare/bareclient/v2/stocks.py
eclcli/bare/bareclient/v2/uefis.py
eclcli/bare/bareclient/v2/versions.py
eclcli/bare/v2/__init__.py
eclcli/bare/v2/flavor.py
eclcli/bare/v2/keypair.py
eclcli/bare/v2/limit.py
eclcli/bare/v2/metadata.py
eclcli/bare/v2/port.py
eclcli/bare/v2/server.py
eclcli/bare/v2/stock.py
eclcli/bare/v2/uefi.py
eclcli/bare/v2/version.py
eclcli-4.6.1.dist-info/AUTHORS
eclcli-4.6.1.dist-info/LICENSE
eclcli-4.6.1.dist-info/METADATA
eclcli-4.6.1.dist-info/WHEEL
eclcli-4.6.1.dist-info/entry_points.txt
eclcli-4.6.1.dist-info/pbr.json
eclcli-4.6.1.dist-info/top_level.txt
eclcli-4.6.1.dist-info/RECORD
