Metadata-Version: 2.1
Name: eclcli
Version: 4.6.1
Summary: CLI for Enterprise Cloud 2.0
Home-page: https://ecl.ntt.com
Author: NTT DOCOMO BUSINESS
License: Apache License, Version 2.0
Platform: UNKNOWN
Classifier: Intended Audience :: Information Technology
Classifier: Intended Audience :: System Administrators
Classifier: License :: OSI Approved :: Apache Software License
Classifier: Operating System :: POSIX :: Linux
Classifier: Programming Language :: Python
Classifier: Programming Language :: Python :: 3
Classifier: Programming Language :: Python :: 3.7
Classifier: Programming Language :: Python :: 3.8
Classifier: Programming Language :: Python :: 3.9
License-File: LICENSE
License-File: AUTHORS
Requires-Dist: pbr>=1.6
Requires-Dist: six>=1.9.0
Requires-Dist: Babel!=2.3.0,!=2.3.1,!=2.3.2,!=2.3.3,!=2.4.0,>=1.3
Requires-Dist: cliff!=1.16.0,!=1.17.0,<3.7.0,>=1.15.0
Requires-Dist: cryptography>=2.9.2
Requires-Dist: eclsdk>=1.7.0
Requires-Dist: future>=0.17.1
Requires-Dist: keystoneauth1<=3.4.0,>=2.1.0
Requires-Dist: openstacksdk<=0.13.0
Requires-Dist: os-client-config>=1.13.1
Requires-Dist: oslo.config>=3.7.0
Requires-Dist: oslo.i18n>=2.1.0
Requires-Dist: oslo.utils>=3.5.0
Requires-Dist: pyparsing<3.0.0
Requires-Dist: python-glanceclient<=2.11.0,>=2.0.0
Requires-Dist: python-keystoneclient!=1.8.0,!=2.1.0,>=1.6.0
Requires-Dist: python-novaclient!=2.33.0,<=9.1.0,>=2.29.0
Requires-Dist: python-cinderclient<=4.3.0,>=1.3.1
Requires-Dist: requests>=2.20.0
Requires-Dist: stevedore>=1.5.0
Requires-Dist: json-merge-patch>=0.2
Requires-Dist: cmd2<0.9.0,>0.8.3
